explaind/__init__.py
explaind/data_paths.py
explaind/epk_model.py
explaind/model_paths.py
explaind/optimizer_paths.py
explaind/cifar_model/__init__.py
explaind/cifar_model/data.py
explaind/cifar_model/model.py
explaind/modulo_model/__init__.py
explaind/modulo_model/data.py
explaind/modulo_model/loss.py
explaind/modulo_model/model.py
explaind-0.0.2.dist-info/licenses/LICENSE
explaind-0.0.2.dist-info/METADATA
explaind-0.0.2.dist-info/WHEEL
explaind-0.0.2.dist-info/top_level.txt
explaind-0.0.2.dist-info/RECORD
