Metadata-Version: 2.4
Name: explaind
Version: 0.0.2
Summary: A unified framework for attributing model components, data, and training dynamics to model behavior.
Author-email: Florian Eichin <feichin@cis.lmu.de>
License: MIT License
Project-URL: Documentation, https://github.com/mainlp/explaind
Project-URL: Homepage, https://github.com/mainlp/explaind
Project-URL: Issues, https://github.com/mainlp/explaind/issues
Project-URL: Repository, https://github.com/mainlp/explaind
Keywords: neural networks,interpretability,explainability,training dynamics,data attribution,model attribution,kernel machines
Classifier: Intended Audience :: Developers
Classifier: Intended Audience :: Science/Research
Classifier: License :: OSI Approved :: MIT License
Classifier: Operating System :: MacOS
Classifier: Operating System :: Microsoft :: Windows
Classifier: Operating System :: POSIX
Classifier: Operating System :: Unix
Classifier: Programming Language :: Python
Classifier: Programming Language :: Python :: 3.12
Classifier: Topic :: Scientific/Engineering
Classifier: Topic :: Scientific/Engineering :: Artificial Intelligence
Requires-Python: >=3.12
License-File: LICENSE
Requires-Dist: numpy>=2.2.6
Requires-Dist: plotly>=6.1.1
Requires-Dist: torch>=2.7.0
Requires-Dist: torchvision>=0.22.0
Requires-Dist: tqdm>=4.67.1
Requires-Dist: umap-learn>=0.5.7
Requires-Dist: tensorboard==2.19.0
Requires-Dist: pandas==2.2.3
Dynamic: license-file
